ndbc_api/__init__.py
ndbc_api/api/__init__.py
ndbc_api/api/handlers/__init__.py
ndbc_api/api/handlers/_base.py
ndbc_api/api/handlers/http/data.py
ndbc_api/api/handlers/http/stations.py
ndbc_api/api/handlers/opendap/data.py
ndbc_api/api/parsers/__init__.py
ndbc_api/api/parsers/http/__init__.py
ndbc_api/api/parsers/http/_base.py
ndbc_api/api/parsers/http/_html.py
ndbc_api/api/parsers/http/_station.py
ndbc_api/api/parsers/http/_xml.py
ndbc_api/api/parsers/http/active_stations.py
ndbc_api/api/parsers/http/adcp.py
ndbc_api/api/parsers/http/cwind.py
ndbc_api/api/parsers/http/historical_stations.py
ndbc_api/api/parsers/http/ocean.py
ndbc_api/api/parsers/http/spec.py
ndbc_api/api/parsers/http/station_historical.py
ndbc_api/api/parsers/http/station_metadata.py
ndbc_api/api/parsers/http/station_realtime.py
ndbc_api/api/parsers/http/stdmet.py
ndbc_api/api/parsers/http/supl.py
ndbc_api/api/parsers/http/swden.py
ndbc_api/api/parsers/http/swdir.py
ndbc_api/api/parsers/http/swdir2.py
ndbc_api/api/parsers/http/swr1.py
ndbc_api/api/parsers/http/swr2.py
ndbc_api/api/parsers/opendap/_base.py
ndbc_api/api/parsers/opendap/adcp.py
ndbc_api/api/parsers/opendap/cwind.py
ndbc_api/api/parsers/opendap/hfradar.py
ndbc_api/api/parsers/opendap/ocean.py
ndbc_api/api/parsers/opendap/pwind.py
ndbc_api/api/parsers/opendap/stdmet.py
ndbc_api/api/parsers/opendap/swden.py
ndbc_api/api/parsers/opendap/wlevel.py
ndbc_api/api/requests/__init__.py
ndbc_api/api/requests/http/__init__.py
ndbc_api/api/requests/http/_base.py
ndbc_api/api/requests/http/_core.py
ndbc_api/api/requests/http/active_stations.py
ndbc_api/api/requests/http/adcp.py
ndbc_api/api/requests/http/cwind.py
ndbc_api/api/requests/http/historical_stations.py
ndbc_api/api/requests/http/ocean.py
ndbc_api/api/requests/http/spec.py
ndbc_api/api/requests/http/station_historical.py
ndbc_api/api/requests/http/station_metadata.py
ndbc_api/api/requests/http/station_realtime.py
ndbc_api/api/requests/http/stdmet.py
ndbc_api/api/requests/http/supl.py
ndbc_api-0.25.6.9.1.dist-info/LICENSE
ndbc_api-0.25.6.9.1.dist-info/METADATA
ndbc_api-0.25.6.9.1.dist-info/WHEEL
ndbc_api-0.25.6.9.1.dist-info/RECORD
