Metadata-Version: 2.3
Name: ndbc-api
Version: 0.25.6.9.1
Summary: A Python API for the National Data Buoy Center.
License: MIT
Author: cdjellen
Author-email: cdjellen@gmail.com
Requires-Python: >=3.9,<3.13
Classifier: License :: OSI Approved :: MIT License
Classifier: Programming Language :: Python :: 3
Classifier: Programming Language :: Python :: 3.9
Classifier: Programming Language :: Python :: 3.10
Classifier: Programming Language :: Python :: 3.11
Classifier: Programming Language :: Python :: 3.12
Requires-Dist: beautifulsoup4 (>=4,<5)
Requires-Dist: h5netcdf (>=1.6.1,<2.0.0)
Requires-Dist: html5lib (>=1.1,<2.0)
Requires-Dist: numpy (>=1.26.3)
Requires-Dist: pandas (>=2.0.0)
Requires-Dist: requests (>=2.10.0)
Requires-Dist: scipy (>=1.7.3)
Requires-Dist: xarray (>=2022.6.0)
